Metadata-Version: 2.1
Name: voice-comm
Version: 0.0.5
Summary: With this package you can create programs which can speak to you and recognize your voice adn run commands. (easy eg.: You can create J.A.R.V.I.S from Iron Man :))
Home-page: UNKNOWN
Author: Da4ndo
Author-email: vrgdnl20@gmail.com
License: UNKNOWN
Keywords: voice_comm,voice comm,voice_comm,Voice Communication,voice communication
Platform: UNKNOWN
Classifier: Development Status :: 5 - Production/Stable
Classifier: Intended Audience :: Education
Classifier: Operating System :: Microsoft :: Windows :: Windows 10
Classifier: License :: OSI Approved :: MIT License
Classifier: Programming Language :: Python :: 3
License-File: LICENSE.txt
